zpui/__init__.py
zpui/main.py
zpui-0.1.1.dist-info/METADATA
zpui-0.1.1.dist-info/WHEEL
zpui-0.1.1.dist-info/licenses/LICENSE
zpui-0.1.1.dist-info/RECORD
