Metadata-Version: 2.3
Name: zpui
Version: 0.1.1
Summary: ZPUI core
Project-URL: Homepage, https://github.com/ZeroPhone/ZPUI
Project-URL: Issues, https://github.com/ZeroPhone/ZPUI/issues
Author-email: "Arya (CRImier)" <arya.voronova@gmail.com>
License-File: LICENSE
Classifier: Operating System :: POSIX :: Linux
Classifier: Programming Language :: Python :: 3
Requires-Python: >=3.8
